<?xml version="1.0" encoding="utf-8"?>
<reebok_main>
  <main_view>
    <left_info>
      <img>http://127.0.0.1:8080/images/reebok/temp/main_banner01_1.jpg</img>
      <link>shop.reebok.co.kr</link>
    </left_info>
    <right_info>
      <product>
        <img>http://127.0.0.1:8080/images/reebok/temp/main_banner02.jpg</img>
        <price>89000</price>
        <link>RPF020401.action?SITE_CD=2&amp;PROD_CD110012</link>
      </product>
      <product>
        <img>http://127.0.0.1:8080/images/reebok/temp/main_banner03.jpg</img>
        <price>69000</price>
        <link>RPF020401.action?SITE_CD=2&amp;PROD_CD110019</link>
      </product>
    </right_info>
  </main_view>
  <main_view>
    <left_info>
      <img>http://127.0.0.1:8080/images/reebok/temp/main_banner01_1.jpg</img>
      <link>shop.reebok.co.kr</link>
    </left_info>
    <right_info>
      <product>
        <img>http://127.0.0.1:8080/images/reebok/temp/main_banner03.jpg</img>
        <price>69000</price>
        <link>RPF020401.action?SITE_CD=2&amp;PROD_CD110019</link>
      </product>
    </right_info>
  </main_view>
</reebok_main>

